webtex/__init__.py
webtex/__version__.py
webtex/interface.py
webtex/server.py
webtex/static/display.js
webtex/static/index.html
webtex/static/main.css
webtex/static/math.js
webtex-0.1.1.dist-info/METADATA
webtex-0.1.1.dist-info/WHEEL
webtex-0.1.1.dist-info/top_level.txt
webtex-0.1.1.dist-info/RECORD
