Metadata-Version: 2.4
Name: webtex
Version: 0.1.1
Summary: A Python interface for web-based LaTeX parsing tool
Author: Nikolay Georgiev
Author-email: Nikolay Georgiev <nygeorgiev@protonmail.com>
License: MIT
Project-URL: Repository, https://github.com/nygeorgiev/webtex
Requires-Python: >=3.11
Requires-Dist: fastapi>=0.119.0
Requires-Dist: uvicorn>=0.37.0
Requires-Dist: websockets>=15.0.1
